tyto/__init__.py
tyto/edam.py
tyto/foo.py
tyto/kisao.py
tyto/ncbi_taxon.py
tyto/ncit.py
tyto/om.py
tyto/paml.py
tyto/pubchem.py
tyto/sbo.py
tyto/sbol2.py
tyto/sbol3.py
tyto/so.py
tyto/tyto.py
tyto/uml.py
tyto/endpoint/__init__.py
tyto/endpoint/endpoint.py
tyto/ontologies/SBO_OWL.owl
tyto/ontologies/example.owl
tyto/ontologies/om-2.0.rdf
tyto/ontologies/so.owl
tyto/ontologies/paml/paml/paml.ttl
tyto/ontologies/paml/uml/uml.ttl
tyto/ontologies/sbol-owl/sbol.rdf
tyto/ontologies/sbol-owl3/sbolowl3.rdf
tyto-1.4.dist-info/LICENSE
tyto-1.4.dist-info/METADATA
tyto-1.4.dist-info/WHEEL
tyto-1.4.dist-info/top_level.txt
tyto-1.4.dist-info/RECORD
